CHANGES
LICENSE
MANIFEST.in
README.rst
setup.cfg
setup.py
Kadabra.egg-info/PKG-INFO
Kadabra.egg-info/SOURCES.txt
Kadabra.egg-info/dependency_links.txt
Kadabra.egg-info/not-zip-safe
Kadabra.egg-info/requires.txt
Kadabra.egg-info/top_level.txt
docs/.gitignore
docs/Makefile
docs/api.rst
docs/collecting.rst
docs/conf.py
docs/configuration.rst
docs/gettingstarted.rst
docs/index.rst
docs/installation.rst
docs/overview.rst
docs/publishing.rst
docs/runninginprod.rst
docs/sending.rst
docs/usingwithinfluxdb.rst
kadabra/__init__.py
kadabra/agent.py
kadabra/channels.py
kadabra/client.py
kadabra/config.py
kadabra/metrics.py
kadabra/publishers.py
kadabra/utils.py
tests/test_agent.py
tests/test_batched_nanny.py
tests/test_batched_receiver.py
tests/test_client.py
tests/test_debug_publisher.py
tests/test_influxdb_publisher.py
tests/test_metrics.py
tests/test_nanny.py
tests/test_nanny_thread.py
tests/test_receiver.py
tests/test_receiver_thread.py
tests/test_redis_channel.py
tests/test_utils.py